{"status": "Succeeded", "recognitionResults": [{"page": 1, "clockwiseOrientation": 359.84, "width": 1770, "height": 2264, "unit": "pixel", "lines": [{"boundingBox": [1349, 164, 1481, 160, 1482, 190, 1349, 194], "text": "AT THE", "words": [{"boundingBox": [1362, 164, 1408, 163, 1410, 193, 1363, 194], "text": "AT"}, {"boundingBox": [1422, 163, 1479, 161, 1481, 190, 1423, 192], "text": "THE"}]}, {"boundingBox": [1226, 218, 1614, 212, 1615, 246, 1227, 252], "text": "MAY 14 JOINT MEETING", "words": [{"boundingBox": [1229, 220, 1303, 221, 1304, 251, 1230, 251], "text": "MAY"}, {"boundingBox": [1315, 221, 1350, 221, 1352, 251, 1316, 251], "text": "14"}, {"boundingBox": [1356, 221, 1450, 219, 1451, 250, 1358, 251], "text": "JOINT"}, {"boundingBox": [1458, 219, 1609, 213, 1611, 246, 1459, 250], "text": "MEETING"}]}, {"boundingBox": [1230, 273, 1572, 274, 1571, 307, 1229, 306], "text": "OF THE TRRF BOARD", "words": [{"boundingBox": [1230, 274, 1274, 275, 1275, 307, 1231, 306], "text": "OF"}, {"boundingBox": [1289, 275, 1354, 276, 1355, 308, 1290, 307], "text": "THE"}, {"boundingBox": [1368, 277, 1454, 277, 1456, 307, 1369, 308], "text": "TRRF"}, {"boundingBox": [1463, 276, 1570, 274, 1571, 305, 1464, 307], "text": "BOARD"}]}, {"boundingBox": [1230, 331, 1561, 330, 1562, 363, 1231, 364], "text": "OF GOVERNORS AND", "words": [{"boundingBox": [1231, 332, 1275, 333, 1276, 364, 1232, 364], "text": "OF"}, {"boundingBox": [1287, 333, 1486, 332, 1488, 363, 1289, 364], "text": "GOVERNORS"}, {"boundingBox": [1493, 332, 1559, 331, 1560, 363, 1494, 363], "text": "AND"}]}, {"boundingBox": [1230, 388, 1586, 386, 1587, 419, 1230, 421], "text": "SCIENTIFIC ADVISORY", "words": [{"boundingBox": [1232, 388, 1417, 388, 1417, 421, 1233, 421], "text": "SCIENTIFIC"}, {"boundingBox": [1428, 388, 1585, 387, 1587, 419, 1428, 421], "text": "ADVISORY"}]}, {"boundingBox": [1229, 446, 1392, 445, 1393, 476, 1230, 477], "text": "COUNCIL.", "words": [{"boundingBox": [1232, 447, 1393, 446, 1393, 478, 1232, 478], "text": "COUNCIL."}]}, {"boundingBox": [245, 853, 821, 848, 821, 884, 246, 889], "text": "Above: Board Chairman Dr. Emil M.", "words": [{"boundingBox": [249, 855, 361, 856, 361, 888, 248, 887], "text": "Above:"}, {"boundingBox": [370, 856, 461, 855, 461, 888, 369, 888], "text": "Board"}, {"boundingBox": [467, 855, 617, 853, 617, 887, 467, 888], "text": "Chairman"}, {"boundingBox": [625, 853, 686, 852, 685, 886, 625, 887], "text": "Dr."}, {"boundingBox": [694, 852, 771, 849, 771, 885, 694, 886], "text": "Emil"}, {"boundingBox": [777, 849, 821, 848, 821, 884, 777, 885], "text": "M."}]}, {"boundingBox": [244, 892, 757, 889, 758, 924, 245, 927], "text": "Mrak, R. M. Powell, TRRF Vice", "words": [{"boundingBox": [248, 894, 350, 894, 350, 927, 248, 927], "text": "Mrak,"}, {"boundingBox": [356, 894, 398, 893, 399, 927, 356, 927], "text": "R."}, {"boundingBox": [405, 893, 454, 893, 454, 926, 405, 927], "text": "M."}, {"boundingBox": [460, 893, 581, 892, 582, 926, 461, 926], "text": "Powell,"}, {"boundingBox": [588, 891, 675, 891, 676, 925, 589, 926], "text": "TRRF"}, {"boundingBox": [688, 890, 756, 890, 757, 925, 689, 925], "text": "Vice"}]}, {"boundingBox": [245, 932, 582, 931, 583, 962, 245, 963], "text": "President Lee Waller.", "words": [{"boundingBox": [249, 932, 396, 934, 397, 964, 250, 964], "text": "President"}, {"boundingBox": [402, 934, 459, 934, 461, 964, 404, 964], "text": "Lee"}, {"boundingBox": [468, 934, 580, 932, 582, 963, 469, 964], "text": "Waller."}]}, {"boundingBox": [249, 1061, 869, 1061, 869, 1096, 250, 1097], "text": "Right: Dr. William J. Darby, president,", "words": [{"boundingBox": [250, 1062, 354, 1063, 354, 1097, 250, 1097], "text": "Right:"}, {"boundingBox": [363, 1063, 423, 1063, 423, 1098, 363, 1097], "text": "Dr."}, {"boundingBox": [430, 1063, 541, 1064, 541, 1098, 430, 1098], "text": "William"}, {"boundingBox": [557, 1064, 592, 1064, 592, 1098, 557, 1098], "text": "J."}, {"boundingBox": [599, 1064, 708, 1063, 707, 1098, 599, 1098], "text": "Darby,"}, {"boundingBox": [715, 1063, 867, 1061, 867, 1098, 714, 1098], "text": "president,"}]}, {"boundingBox": [250, 1100, 836, 1099, 837, 1134, 250, 1135], "text": "The Nutrition Foundation and new pub-", "words": [{"boundingBox": [252, 1100, 310, 1101, 312, 1135, 253, 1134], "text": "The"}, {"boundingBox": [317, 1102, 457, 1104, 458, 1135, 318, 1135], "text": "Nutrition"}, {"boundingBox": [466, 1104, 632, 1104, 633, 1135, 467, 1135], "text": "Foundation"}, {"boundingBox": [639, 1104, 693, 1103, 694, 1135, 640, 1135], "text": "and"}, {"boundingBox": [700, 1103, 758, 1102, 759, 1134, 701, 1135], "text": "new"}, {"boundingBox": [767, 1102, 837, 1100, 838, 1134, 768, 1134], "text": "pub-"}]}, {"boundingBox": [248, 1139, 818, 1138, 819, 1173, 249, 1174], "text": "lic member, and Dr. Owen Fennema,", "words": [{"boundingBox": [249, 1140, 292, 1140, 293, 1174, 250, 1173], "text": "lic"}, {"boundingBox": [299, 1140, 446, 1140, 447, 1175, 300, 1174], "text": "member,"}, {"boundingBox": [453, 1140, 509, 1140, 509, 1175, 453, 1175], "text": "and"}, {"boundingBox": [516, 1140, 576, 1140, 576, 1175, 516, 1175], "text": "Dr."}, {"boundingBox": [583, 1140, 665, 1140, 665, 1175, 583, 1175], "text": "Owen"}, {"boundingBox": [674, 1140, 819, 1139, 818, 1174, 673, 1175], "text": "Fennema,"}]}, {"boundingBox": [250, 1176, 628, 1181, 627, 1215, 249, 1210], "text": "University of Wisconsin.", "words": [{"boundingBox": [250, 1178, 414, 1179, 414, 1213, 250, 1212], "text": "University"}, {"boundingBox": [420, 1179, 458, 1179, 458, 1213, 420, 1213], "text": "of"}, {"boundingBox": [469, 1180, 629, 1184, 629, 1214, 469, 1213], "text": "Wisconsin."}]}, {"boundingBox": [1231, 1358, 1661, 1357, 1662, 1394, 1232, 1395], "text": "Left: Edward Simons, Con-", "words": [{"boundingBox": [1237, 1358, 1324, 1360, 1325, 1395, 1237, 1396], "text": "Left:"}, {"boundingBox": [1332, 1360, 1447, 1361, 1447, 1394, 1332, 1395], "text": "Edward"}, {"boundingBox": [1454, 1361, 1582, 1360, 1583, 1394, 1455, 1394], "text": "Simons,"}, {"boundingBox": [1590, 1360, 1660, 1359, 1660, 1394, 1590, 1394], "text": "Con-"}]}, {"boundingBox": [1234, 1399, 1666, 1394, 1667, 1430, 1235, 1435], "text": "sulting Engineer, Dr. W. F.", "words": [{"boundingBox": [1238, 1400, 1341, 1401, 1342, 1434, 1238, 1436], "text": "sulting"}, {"boundingBox": [1348, 1401, 1505, 1399, 1506, 1433, 1349, 1434], "text": "Engineer,"}, {"boundingBox": [1512, 1399, 1572, 1398, 1574, 1432, 1513, 1432], "text": "Dr."}, {"boundingBox": [1579, 1397, 1630, 1396, 1632, 1431, 1581, 1432], "text": "W."}, {"boundingBox": [1637, 1396, 1664, 1395, 1666, 1431, 1639, 1431], "text": "F."}]}, {"boundingBox": [1235, 1437, 1595, 1436, 1596, 1471, 1236, 1472], "text": "Stoecker, University of", "words": [{"boundingBox": [1238, 1437, 1385, 1438, 1386, 1471, 1238, 1472], "text": "Stoecker,"}, {"boundingBox": [1392, 1438, 1556, 1438, 1556, 1470, 1393, 1471], "text": "University"}, {"boundingBox": [1563, 1438, 1596, 1438, 1596, 1470, 1563, 1470], "text": "of"}]}, {"boundingBox": [1236, 1476, 1623, 1472, 1624, 1507, 1237, 1511], "text": "Illinois, and Dr. William", "words": [{"boundingBox": [1237, 1476, 1365, 1475, 1366, 1508, 1237, 1512], "text": "Illinois,"}, {"boundingBox": [1372, 1475, 1426, 1475, 1427, 1507, 1373, 1508], "text": "and"}, {"boundingBox": [1433, 1475, 1494, 1475, 1495, 1507, 1434, 1507], "text": "Dr."}, {"boundingBox": [1501, 1475, 1614, 1474, 1615, 1507, 1502, 1507], "text": "William"}]}, {"boundingBox": [1237, 1514, 1653, 1515, 1652, 1549, 1236, 1547], "text": "Hoover, American Institute", "words": [{"boundingBox": [1237, 1514, 1363, 1515, 1363, 1549, 1237, 1549], "text": "Hoover,"}, {"boundingBox": [1369, 1515, 1520, 1516, 1520, 1549, 1369, 1549], "text": "American"}, {"boundingBox": [1527, 1516, 1652, 1516, 1652, 1550, 1527, 1549], "text": "Institute"}]}, {"boundingBox": [1235, 1552, 1385, 1555, 1385, 1587, 1234, 1584], "text": "of Baking.", "words": [{"boundingBox": [1237, 1553, 1268, 1554, 1268, 1586, 1237, 1585], "text": "of"}, {"boundingBox": [1274, 1554, 1384, 1555, 1384, 1588, 1275, 1586], "text": "Baking."}]}, {"boundingBox": [345, 1821, 825, 1830, 824, 1866, 344, 1856], "text": "Right: Dr. Robert Hardenburg,", "words": [{"boundingBox": [347, 1821, 449, 1824, 449, 1859, 348, 1858], "text": "Right:"}, {"boundingBox": [458, 1824, 520, 1825, 520, 1861, 459, 1860], "text": "Dr."}, {"boundingBox": [527, 1826, 632, 1828, 631, 1863, 527, 1861], "text": "Robert"}, {"boundingBox": [639, 1828, 824, 1831, 822, 1866, 638, 1863], "text": "Hardenburg,"}]}, {"boundingBox": [346, 1859, 856, 1864, 855, 1902, 345, 1897], "text": "U. S. Department of Agriculture,", "words": [{"boundingBox": [346, 1859, 390, 1860, 390, 1898, 347, 1898], "text": "U."}, {"boundingBox": [397, 1861, 431, 1862, 431, 1899, 398, 1898], "text": "S."}, {"boundingBox": [438, 1862, 621, 1866, 621, 1900, 439, 1899], "text": "Department"}, {"boundingBox": [628, 1866, 659, 1866, 659, 1900, 629, 1900], "text": "of"}, {"boundingBox": [667, 1866, 854, 1865, 854, 1903, 667, 1901], "text": "Agriculture,"}]}, {"boundingBox": [345, 1899, 789, 1901, 788, 1937, 344, 1935], "text": "and Sam Cecil, University of", "words": [{"boundingBox": [346, 1900, 400, 1900, 399, 1936, 345, 1935], "text": "and"}, {"boundingBox": [407, 1900, 463, 1900, 462, 1937, 406, 1936], "text": "Sam"}, {"boundingBox": [482, 1901, 581, 1901, 580, 1937, 481, 1937], "text": "Cecil,"}, {"boundingBox": [588, 1901, 752, 1902, 751, 1937, 587, 1937], "text": "University"}, {"boundingBox": [759, 1902, 789, 1902, 788, 1937, 758, 1937], "text": "of"}]}, {"boundingBox": [350, 1938, 477, 1942, 476, 1976, 348, 1971], "text": "Georgia.", "words": [{"boundingBox": [351, 1939, 477, 1943, 476, 1976, 349, 1972], "text": "Georgia."}]}, {"boundingBox": [878, 2186, 926, 2183, 927, 2207, 879, 2210], "text": "-5-", "words": [{"boundingBox": [879, 2185, 925, 2183, 926, 2206, 880, 2209], "text": "-5-"}]}]}]}