{"status": "Succeeded", "recognitionResults": [{"page": 1, "clockwiseOrientation": 359.25, "width": 1786, "height": 2283, "unit": "pixel", "lines": [{"boundingBox": [726, 167, 867, 166, 868, 194, 727, 195], "text": "TABLE 13", "words": [{"boundingBox": [732, 169, 818, 167, 818, 194, 734, 196], "text": "TABLE"}, {"boundingBox": [836, 168, 868, 168, 868, 194, 836, 194], "text": "13"}]}, {"boundingBox": [270, 234, 1324, 237, 1324, 270, 269, 267], "text": "The Ratio Of The Risk Of CHD Of The Special Intervention Group", "words": [{"boundingBox": [274, 237, 325, 237, 325, 266, 274, 266], "text": "The"}, {"boundingBox": [340, 237, 427, 237, 427, 266, 340, 266], "text": "Ratio"}, {"boundingBox": [440, 237, 480, 237, 480, 266, 440, 266], "text": "Of"}, {"boundingBox": [495, 237, 546, 237, 546, 266, 495, 266], "text": "The"}, {"boundingBox": [561, 237, 631, 237, 631, 266, 561, 266], "text": "Risk"}, {"boundingBox": [646, 237, 684, 237, 684, 267, 646, 267], "text": "Of"}, {"boundingBox": [699, 237, 750, 237, 750, 267, 699, 267], "text": "CHD"}, {"boundingBox": [765, 237, 803, 237, 803, 267, 765, 267], "text": "Of"}, {"boundingBox": [818, 237, 871, 237, 871, 267, 818, 267], "text": "The"}, {"boundingBox": [886, 237, 1008, 237, 1008, 268, 886, 268], "text": "Special"}, {"boundingBox": [1023, 237, 1227, 237, 1227, 270, 1023, 268], "text": "Intervention"}, {"boundingBox": [1244, 237, 1324, 238, 1324, 270, 1244, 270], "text": "Group"}]}, {"boundingBox": [433, 301, 1156, 300, 1157, 335, 434, 336], "text": "To The Usual Care Group By Clinical Center", "words": [{"boundingBox": [443, 305, 475, 305, 477, 333, 445, 333], "text": "To"}, {"boundingBox": [493, 305, 545, 306, 547, 334, 495, 334], "text": "The"}, {"boundingBox": [559, 306, 649, 305, 650, 335, 561, 334], "text": "Usual"}, {"boundingBox": [667, 305, 737, 305, 738, 336, 668, 336], "text": "Care"}, {"boundingBox": [748, 305, 833, 305, 835, 336, 749, 336], "text": "Group"}, {"boundingBox": [850, 305, 885, 304, 887, 336, 851, 336], "text": "By"}, {"boundingBox": [903, 304, 1041, 303, 1042, 336, 904, 336], "text": "Clinical"}, {"boundingBox": [1056, 303, 1156, 301, 1157, 335, 1056, 336], "text": "Center"}]}, {"boundingBox": [140, 407, 405, 408, 404, 440, 139, 439], "text": "Clinical Center", "words": [{"boundingBox": [140, 408, 282, 410, 283, 440, 140, 439], "text": "Clinical"}, {"boundingBox": [294, 410, 400, 408, 401, 438, 294, 440], "text": "Center"}]}, {"boundingBox": [563, 406, 892, 407, 891, 438, 562, 436], "text": "No. of Participants", "words": [{"boundingBox": [563, 406, 622, 407, 623, 437, 565, 436], "text": "No."}, {"boundingBox": [634, 408, 670, 408, 672, 438, 635, 437], "text": "of"}, {"boundingBox": [684, 408, 890, 408, 892, 437, 686, 438], "text": "Participants"}]}, {"boundingBox": [1079, 377, 1210, 376, 1210, 403, 1080, 405], "text": "Relative", "words": [{"boundingBox": [1080, 379, 1210, 376, 1210, 405, 1080, 404], "text": "Relative"}]}, {"boundingBox": [560, 443, 602, 442, 603, 469, 560, 471], "text": "UC", "words": [{"boundingBox": [564, 442, 600, 441, 601, 468, 565, 469], "text": "UC"}]}, {"boundingBox": [1091, 408, 1217, 407, 1218, 436, 1092, 436], "text": "Risk of", "words": [{"boundingBox": [1092, 410, 1159, 410, 1161, 437, 1093, 436], "text": "Risk"}, {"boundingBox": [1178, 409, 1213, 408, 1215, 436, 1180, 437], "text": "of"}]}, {"boundingBox": [834, 445, 882, 441, 883, 470, 835, 475], "text": "SI", "words": [{"boundingBox": [837, 444, 874, 441, 877, 470, 840, 473], "text": "SI"}]}, {"boundingBox": [1056, 438, 1241, 437, 1242, 472, 1057, 472], "text": "CHD (SI/UC)", "words": [{"boundingBox": [1059, 441, 1111, 441, 1112, 471, 1060, 471], "text": "CHD"}, {"boundingBox": [1129, 441, 1240, 438, 1241, 472, 1130, 471], "text": "(SI/UC)"}]}, {"boundingBox": [71, 563, 108, 566, 108, 588, 72, 586], "text": "A.", "words": [{"boundingBox": [74, 562, 107, 564, 106, 587, 72, 585], "text": "A."}]}, {"boundingBox": [130, 564, 298, 565, 297, 590, 129, 589], "text": "Baltimore", "words": [{"boundingBox": [139, 566, 293, 565, 294, 590, 140, 589], "text": "Baltimore"}]}, {"boundingBox": [561, 559, 608, 556, 610, 584, 563, 586], "text": "248", "words": [{"boundingBox": [564, 557, 607, 555, 608, 583, 565, 585], "text": "248"}]}, {"boundingBox": [830, 558, 886, 557, 887, 583, 832, 584], "text": "261", "words": [{"boundingBox": [836, 557, 884, 557, 885, 582, 836, 583], "text": "261"}]}, {"boundingBox": [1099, 563, 1153, 559, 1155, 586, 1100, 589], "text": "656", "words": [{"boundingBox": [1108, 561, 1152, 558, 1153, 585, 1110, 588], "text": "656"}]}, {"boundingBox": [64, 631, 120, 633, 119, 658, 63, 655], "text": "B.", "words": [{"boundingBox": [72, 630, 110, 632, 109, 657, 71, 655], "text": "B."}]}, {"boundingBox": [130, 629, 278, 630, 278, 659, 129, 658], "text": "New York", "words": [{"boundingBox": [138, 632, 188, 633, 188, 658, 138, 656], "text": "New"}, {"boundingBox": [210, 632, 276, 630, 276, 659, 211, 658], "text": "York"}]}, {"boundingBox": [563, 629, 613, 626, 614, 651, 565, 654], "text": "335", "words": [{"boundingBox": [564, 628, 612, 625, 613, 650, 565, 653], "text": "335"}]}, {"boundingBox": [831, 622, 886, 624, 887, 652, 832, 650], "text": "342", "words": [{"boundingBox": [836, 622, 886, 623, 885, 651, 835, 650], "text": "342"}]}, {"boundingBox": [1097, 628, 1165, 627, 1166, 654, 1098, 654], "text": ". 648", "words": [{"boundingBox": [1096, 626, 1105, 626, 1105, 653, 1096, 653], "text": "."}, {"boundingBox": [1111, 626, 1163, 626, 1163, 653, 1111, 653], "text": "648"}]}, {"boundingBox": [73, 699, 110, 699, 110, 724, 73, 724], "text": "C.", "words": [{"boundingBox": [73, 699, 109, 699, 109, 724, 73, 724], "text": "C."}]}, {"boundingBox": [126, 697, 328, 698, 327, 726, 126, 726], "text": "Minneapolis", "words": [{"boundingBox": [138, 698, 328, 699, 328, 727, 137, 726], "text": "Minneapolis"}]}, {"boundingBox": [561, 695, 610, 693, 611, 720, 562, 721], "text": "269", "words": [{"boundingBox": [563, 693, 608, 692, 609, 719, 564, 720], "text": "269"}]}, {"boundingBox": [828, 693, 886, 693, 887, 721, 829, 721], "text": "270", "words": [{"boundingBox": [835, 693, 885, 693, 885, 721, 835, 721], "text": "270"}]}, {"boundingBox": [1096, 695, 1157, 694, 1157, 721, 1097, 723], "text": ". 632", "words": [{"boundingBox": [1095, 695, 1104, 694, 1105, 722, 1095, 722], "text": "."}, {"boundingBox": [1110, 694, 1154, 693, 1155, 721, 1110, 722], "text": "632"}]}, {"boundingBox": [69, 767, 104, 765, 105, 787, 71, 790], "text": "D.", "words": [{"boundingBox": [71, 766, 101, 764, 103, 787, 72, 789], "text": "D."}]}, {"boundingBox": [131, 763, 359, 764, 358, 793, 130, 792], "text": "San Francisco", "words": [{"boundingBox": [140, 765, 191, 765, 190, 793, 140, 792], "text": "San"}, {"boundingBox": [209, 765, 359, 764, 359, 793, 208, 793], "text": "Francisco"}]}, {"boundingBox": [557, 767, 610, 763, 611, 786, 558, 790], "text": "234", "words": [{"boundingBox": [563, 766, 608, 763, 609, 786, 565, 789], "text": "234"}]}, {"boundingBox": [831, 761, 885, 761, 886, 788, 832, 788], "text": "250", "words": [{"boundingBox": [836, 761, 885, 761, 885, 788, 836, 788], "text": "250"}]}, {"boundingBox": [1095, 763, 1165, 762, 1165, 792, 1095, 791], "text": ". 742", "words": [{"boundingBox": [1097, 762, 1105, 762, 1105, 792, 1097, 792], "text": "."}, {"boundingBox": [1111, 762, 1165, 762, 1165, 792, 1111, 792], "text": "742"}]}, {"boundingBox": [110, 830, 291, 832, 291, 862, 109, 860], "text": "St. Louis", "words": [{"boundingBox": [138, 832, 196, 833, 197, 861, 139, 860], "text": "St."}, {"boundingBox": [208, 833, 291, 832, 291, 862, 208, 861], "text": "Louis"}]}, {"boundingBox": [560, 833, 616, 832, 617, 857, 561, 858], "text": "141", "words": [{"boundingBox": [562, 832, 616, 831, 616, 856, 563, 857], "text": "141"}]}, {"boundingBox": [830, 830, 886, 830, 888, 857, 832, 856], "text": "149", "words": [{"boundingBox": [835, 829, 887, 829, 887, 856, 835, 856], "text": "149"}]}, {"boundingBox": [1096, 832, 1154, 831, 1155, 857, 1098, 860], "text": ". 665", "words": [{"boundingBox": [1095, 831, 1103, 831, 1104, 859, 1096, 859], "text": "."}, {"boundingBox": [1109, 831, 1153, 829, 1154, 857, 1110, 859], "text": "665"}]}, {"boundingBox": [70, 896, 374, 900, 373, 929, 69, 926], "text": "F. Boston Harvard", "words": [{"boundingBox": [73, 900, 106, 901, 106, 924, 73, 922], "text": "F."}, {"boundingBox": [139, 902, 239, 902, 240, 928, 139, 925], "text": "Boston"}, {"boundingBox": [256, 902, 374, 900, 375, 928, 257, 928], "text": "Harvard"}]}, {"boundingBox": [558, 900, 611, 897, 612, 923, 558, 926], "text": "285", "words": [{"boundingBox": [563, 898, 610, 896, 611, 922, 565, 925], "text": "285"}]}, {"boundingBox": [831, 899, 888, 897, 889, 922, 832, 925], "text": "286", "words": [{"boundingBox": [835, 898, 886, 896, 887, 922, 837, 924], "text": "286"}]}, {"boundingBox": [1093, 899, 1164, 895, 1166, 921, 1096, 925], "text": ". 804", "words": [{"boundingBox": [1094, 898, 1104, 898, 1106, 924, 1095, 924], "text": "."}, {"boundingBox": [1109, 898, 1161, 895, 1163, 921, 1111, 923], "text": "804"}]}, {"boundingBox": [71, 968, 138, 969, 137, 995, 70, 993], "text": "G.", "words": [{"boundingBox": [71, 967, 109, 968, 109, 994, 71, 993], "text": "G."}]}, {"boundingBox": [561, 967, 615, 963, 617, 988, 562, 992], "text": "221", "words": [{"boundingBox": [563, 965, 613, 962, 615, 988, 565, 991], "text": "221"}]}, {"boundingBox": [831, 963, 885, 962, 886, 989, 832, 991], "text": "212", "words": [{"boundingBox": [835, 962, 884, 961, 885, 989, 836, 990], "text": "212"}]}, {"boundingBox": [1101, 969, 1157, 966, 1158, 990, 1102, 992], "text": "603", "words": [{"boundingBox": [1108, 967, 1156, 965, 1157, 989, 1109, 991], "text": "603"}]}, {"boundingBox": [69, 1034, 448, 1036, 447, 1065, 68, 1063], "text": "H. Chic. Northwestern", "words": [{"boundingBox": [69, 1035, 108, 1036, 109, 1062, 70, 1061], "text": "H."}, {"boundingBox": [140, 1036, 228, 1037, 229, 1065, 141, 1063], "text": "Chic."}, {"boundingBox": [241, 1037, 444, 1036, 445, 1063, 242, 1065], "text": "Northwestern"}]}, {"boundingBox": [561, 1033, 611, 1034, 612, 1060, 562, 1060], "text": "152", "words": [{"boundingBox": [564, 1032, 611, 1032, 611, 1059, 564, 1059], "text": "152"}]}, {"boundingBox": [833, 1033, 886, 1031, 887, 1056, 835, 1058], "text": "154", "words": [{"boundingBox": [836, 1032, 884, 1031, 885, 1055, 837, 1057], "text": "154"}]}, {"boundingBox": [1096, 1035, 1155, 1034, 1155, 1060, 1095, 1062], "text": ". 602", "words": [{"boundingBox": [1094, 1035, 1103, 1034, 1103, 1061, 1094, 1061], "text": "."}, {"boundingBox": [1108, 1034, 1153, 1033, 1154, 1060, 1109, 1061], "text": "602"}]}, {"boundingBox": [68, 1100, 421, 1102, 420, 1133, 67, 1132], "text": "I. Chic. St. Joseph", "words": [{"boundingBox": [72, 1101, 110, 1102, 110, 1131, 72, 1130], "text": "I."}, {"boundingBox": [139, 1102, 229, 1103, 230, 1133, 140, 1132], "text": "Chic."}, {"boundingBox": [241, 1103, 297, 1103, 297, 1134, 241, 1134], "text": "St."}, {"boundingBox": [312, 1103, 411, 1102, 412, 1132, 312, 1134], "text": "Joseph"}]}, {"boundingBox": [558, 1101, 612, 1098, 613, 1125, 559, 1128], "text": "141", "words": [{"boundingBox": [562, 1100, 611, 1098, 612, 1124, 564, 1127], "text": "141"}]}, {"boundingBox": [830, 1098, 875, 1097, 878, 1123, 833, 1124], "text": "133", "words": [{"boundingBox": [836, 1097, 876, 1096, 876, 1122, 836, 1123], "text": "133"}]}, {"boundingBox": [1092, 1103, 1163, 1100, 1165, 1127, 1094, 1130], "text": ". 550", "words": [{"boundingBox": [1093, 1102, 1102, 1102, 1103, 1129, 1094, 1129], "text": "."}, {"boundingBox": [1107, 1102, 1161, 1100, 1163, 1127, 1109, 1129], "text": "550"}]}, {"boundingBox": [91, 1169, 406, 1171, 405, 1202, 91, 1201], "text": ". Chic. University", "words": [{"boundingBox": [92, 1170, 113, 1170, 111, 1201, 91, 1201], "text": "."}, {"boundingBox": [139, 1171, 232, 1173, 231, 1201, 138, 1201], "text": "Chic."}, {"boundingBox": [240, 1173, 405, 1173, 403, 1202, 239, 1201], "text": "University"}]}, {"boundingBox": [575, 1172, 610, 1170, 612, 1192, 577, 1195], "text": "90", "words": [{"boundingBox": [580, 1171, 609, 1169, 611, 1192, 582, 1194], "text": "90"}]}, {"boundingBox": [851, 1169, 882, 1166, 884, 1188, 854, 1191], "text": "88", "words": [{"boundingBox": [853, 1168, 881, 1165, 883, 1187, 855, 1190], "text": "88"}]}, {"boundingBox": [1100, 1170, 1154, 1167, 1156, 1194, 1102, 1197], "text": "592", "words": [{"boundingBox": [1108, 1169, 1153, 1167, 1154, 1193, 1109, 1196], "text": "592"}]}, {"boundingBox": [60, 1237, 276, 1239, 275, 1269, 59, 1267], "text": "K. Portland", "words": [{"boundingBox": [68, 1238, 110, 1238, 109, 1268, 68, 1268], "text": "K."}, {"boundingBox": [138, 1239, 276, 1240, 276, 1268, 137, 1268], "text": "Portland"}]}, {"boundingBox": [563, 1239, 615, 1236, 616, 1261, 564, 1264], "text": "268", "words": [{"boundingBox": [564, 1238, 614, 1236, 615, 1260, 565, 1263], "text": "268"}]}, {"boundingBox": [834, 1234, 886, 1235, 887, 1262, 834, 1261], "text": "263", "words": [{"boundingBox": [837, 1234, 886, 1234, 885, 1261, 837, 1261], "text": "263"}]}, {"boundingBox": [1096, 1237, 1156, 1237, 1158, 1264, 1097, 1265], "text": ". 712", "words": [{"boundingBox": [1095, 1236, 1103, 1236, 1103, 1264, 1095, 1264], "text": "."}, {"boundingBox": [1108, 1236, 1157, 1236, 1157, 1264, 1109, 1264], "text": "712"}]}, {"boundingBox": [68, 1309, 105, 1309, 105, 1334, 69, 1334], "text": "L.", "words": [{"boundingBox": [69, 1309, 104, 1309, 104, 1334, 69, 1334], "text": "L."}]}, {"boundingBox": [127, 1305, 431, 1306, 430, 1336, 126, 1335], "text": "Boston University", "words": [{"boundingBox": [137, 1306, 243, 1306, 242, 1336, 136, 1335], "text": "Boston"}, {"boundingBox": [258, 1306, 430, 1307, 429, 1337, 257, 1336], "text": "University"}]}, {"boundingBox": [561, 1304, 610, 1304, 611, 1332, 562, 1332], "text": "249", "words": [{"boundingBox": [564, 1304, 609, 1304, 609, 1332, 564, 1332], "text": "249"}]}, {"boundingBox": [840, 1304, 886, 1303, 887, 1329, 842, 1330], "text": "240", "words": [{"boundingBox": [839, 1304, 886, 1302, 886, 1328, 839, 1329], "text": "240"}]}, {"boundingBox": [1095, 1306, 1156, 1307, 1157, 1333, 1095, 1334], "text": ". 652", "words": [{"boundingBox": [1094, 1305, 1102, 1305, 1102, 1333, 1094, 1333], "text": "."}, {"boundingBox": [1108, 1305, 1156, 1305, 1156, 1333, 1108, 1333], "text": "652"}]}, {"boundingBox": [68, 1378, 102, 1376, 103, 1397, 69, 1399], "text": "M.", "words": [{"boundingBox": [69, 1377, 101, 1376, 102, 1396, 70, 1398], "text": "M."}]}, {"boundingBox": [126, 1374, 245, 1377, 244, 1404, 125, 1401], "text": "Dayton", "words": [{"boundingBox": [137, 1376, 238, 1378, 239, 1402, 138, 1401], "text": "Dayton"}]}, {"boundingBox": [558, 1375, 611, 1372, 612, 1396, 559, 1399], "text": "298", "words": [{"boundingBox": [563, 1374, 610, 1372, 611, 1395, 565, 1398], "text": "298"}]}, {"boundingBox": [827, 1372, 887, 1371, 889, 1397, 829, 1398], "text": "288", "words": [{"boundingBox": [835, 1371, 887, 1370, 887, 1396, 835, 1397], "text": "288"}]}, {"boundingBox": [1101, 1373, 1155, 1371, 1155, 1397, 1101, 1400], "text": "581", "words": [{"boundingBox": [1106, 1372, 1153, 1370, 1154, 1396, 1107, 1398], "text": "581"}]}, {"boundingBox": [67, 1440, 239, 1444, 238, 1472, 66, 1469], "text": "N. Newark", "words": [{"boundingBox": [68, 1442, 106, 1442, 107, 1470, 70, 1468], "text": "N."}, {"boundingBox": [137, 1443, 238, 1444, 238, 1471, 138, 1470], "text": "Newark"}]}, {"boundingBox": [560, 1440, 616, 1437, 617, 1463, 562, 1467], "text": "162", "words": [{"boundingBox": [562, 1439, 614, 1436, 616, 1463, 564, 1466], "text": "162"}]}, {"boundingBox": [831, 1442, 876, 1443, 878, 1469, 833, 1468], "text": "152", "words": [{"boundingBox": [836, 1442, 877, 1442, 877, 1468, 835, 1468], "text": "152"}]}, {"boundingBox": [1092, 1442, 1152, 1439, 1153, 1467, 1093, 1470], "text": ". 467", "words": [{"boundingBox": [1093, 1441, 1100, 1441, 1102, 1469, 1094, 1469], "text": "."}, {"boundingBox": [1106, 1441, 1151, 1439, 1152, 1466, 1107, 1469], "text": "467"}]}, {"boundingBox": [68, 1508, 349, 1511, 348, 1541, 67, 1538], "text": "0. Philadelphia", "words": [{"boundingBox": [69, 1511, 106, 1512, 107, 1537, 71, 1536], "text": "0.", "confidence": "Low"}, {"boundingBox": [138, 1512, 343, 1511, 343, 1541, 139, 1538], "text": "Philadelphia"}]}, {"boundingBox": [561, 1508, 611, 1506, 613, 1533, 563, 1536], "text": "178", "words": [{"boundingBox": [564, 1507, 610, 1505, 612, 1533, 565, 1535], "text": "178"}]}, {"boundingBox": [841, 1507, 885, 1506, 886, 1535, 842, 1536], "text": "173", "words": [{"boundingBox": [840, 1507, 884, 1505, 885, 1534, 840, 1535], "text": "173", "confidence": "Low"}]}, {"boundingBox": [1091, 1511, 1163, 1506, 1166, 1533, 1091, 1538], "text": ". 666", "words": [{"boundingBox": [1092, 1509, 1100, 1509, 1102, 1537, 1094, 1537], "text": "."}, {"boundingBox": [1105, 1508, 1159, 1505, 1161, 1533, 1107, 1536], "text": "666"}]}, {"boundingBox": [64, 1579, 121, 1580, 121, 1604, 63, 1603], "text": "P.", "words": [{"boundingBox": [69, 1579, 107, 1579, 107, 1603, 68, 1603], "text": "P."}]}, {"boundingBox": [126, 1579, 318, 1582, 317, 1609, 125, 1607], "text": "Birmingham", "words": [{"boundingBox": [137, 1580, 308, 1582, 309, 1609, 136, 1607], "text": "Birmingham"}]}, {"boundingBox": [561, 1578, 614, 1575, 616, 1600, 563, 1603], "text": "132", "words": [{"boundingBox": [563, 1577, 613, 1574, 615, 1599, 565, 1602], "text": "132"}]}, {"boundingBox": [831, 1574, 886, 1574, 887, 1601, 832, 1601], "text": "126", "words": [{"boundingBox": [836, 1574, 886, 1574, 886, 1601, 836, 1601], "text": "126"}]}, {"boundingBox": [1093, 1577, 1164, 1576, 1165, 1602, 1094, 1604], "text": ". 603", "words": [{"boundingBox": [1092, 1577, 1101, 1576, 1101, 1603, 1092, 1603], "text": "."}, {"boundingBox": [1106, 1576, 1160, 1575, 1161, 1602, 1107, 1603], "text": "603"}]}, {"boundingBox": [69, 1647, 105, 1648, 104, 1674, 69, 1673], "text": "Q.", "words": [{"boundingBox": [70, 1646, 103, 1647, 102, 1673, 69, 1672], "text": "Q."}]}, {"boundingBox": [126, 1646, 304, 1650, 303, 1678, 125, 1674], "text": "Pittsburgh", "words": [{"boundingBox": [137, 1647, 304, 1650, 304, 1678, 137, 1675], "text": "Pittsburgh"}]}, {"boundingBox": [561, 1644, 613, 1643, 614, 1671, 562, 1672], "text": "240", "words": [{"boundingBox": [564, 1643, 612, 1642, 613, 1670, 564, 1671], "text": "240"}]}, {"boundingBox": [833, 1644, 886, 1643, 887, 1669, 834, 1670], "text": "244", "words": [{"boundingBox": [835, 1643, 886, 1642, 886, 1668, 836, 1669], "text": "244"}]}, {"boundingBox": [1100, 1643, 1152, 1642, 1154, 1668, 1102, 1670], "text": "623", "words": [{"boundingBox": [1106, 1642, 1153, 1641, 1153, 1668, 1107, 1669], "text": "623"}]}, {"boundingBox": [68, 1713, 347, 1715, 346, 1744, 67, 1743], "text": "R. Chicago Rush", "words": [{"boundingBox": [70, 1715, 107, 1715, 108, 1743, 71, 1742], "text": "R."}, {"boundingBox": [139, 1715, 259, 1715, 260, 1744, 139, 1743], "text": "Chicago"}, {"boundingBox": [273, 1715, 343, 1715, 344, 1743, 274, 1744], "text": "Rush"}]}, {"boundingBox": [576, 1710, 615, 1709, 615, 1738, 576, 1739], "text": "61", "words": [{"boundingBox": [581, 1709, 613, 1709, 614, 1738, 581, 1738], "text": "61"}]}, {"boundingBox": [849, 1712, 886, 1709, 887, 1733, 850, 1736], "text": "62", "words": [{"boundingBox": [851, 1711, 884, 1709, 886, 1733, 853, 1735], "text": "62"}]}, {"boundingBox": [1090, 1711, 1156, 1710, 1157, 1738, 1091, 1739], "text": ".564", "words": [{"boundingBox": [1093, 1710, 1154, 1710, 1155, 1738, 1093, 1738], "text": ".564"}]}, {"boundingBox": [94, 1781, 254, 1782, 253, 1811, 94, 1811], "text": "Rutgers", "words": [{"boundingBox": [138, 1783, 253, 1783, 254, 1811, 137, 1811], "text": "Rutgers"}]}, {"boundingBox": [559, 1782, 613, 1779, 615, 1805, 562, 1808], "text": "105", "words": [{"boundingBox": [563, 1781, 612, 1778, 613, 1804, 565, 1807], "text": "105"}]}, {"boundingBox": [831, 1780, 884, 1775, 887, 1801, 834, 1806], "text": "104", "words": [{"boundingBox": [835, 1779, 883, 1774, 886, 1800, 838, 1805], "text": "104"}]}, {"boundingBox": [1101, 1780, 1155, 1778, 1156, 1806, 1102, 1809], "text": "786", "words": [{"boundingBox": [1106, 1779, 1152, 1777, 1154, 1806, 1107, 1808], "text": "786"}]}, {"boundingBox": [59, 1849, 274, 1848, 275, 1876, 60, 1876], "text": "T. Columbia", "words": [{"boundingBox": [72, 1850, 107, 1850, 106, 1877, 71, 1877], "text": "T."}, {"boundingBox": [138, 1850, 272, 1849, 274, 1876, 138, 1877], "text": "Columbia"}]}, {"boundingBox": [559, 1848, 615, 1845, 615, 1873, 560, 1876], "text": "147", "words": [{"boundingBox": [563, 1847, 614, 1844, 615, 1872, 565, 1875], "text": "147"}]}, {"boundingBox": [832, 1846, 886, 1847, 887, 1874, 833, 1873], "text": "140", "words": [{"boundingBox": [835, 1846, 885, 1846, 885, 1873, 835, 1873], "text": "140"}]}, {"boundingBox": [1090, 1850, 1155, 1847, 1156, 1874, 1091, 1878], "text": ". 424", "words": [{"boundingBox": [1091, 1849, 1098, 1849, 1100, 1877, 1092, 1877], "text": "."}, {"boundingBox": [1104, 1849, 1152, 1846, 1154, 1874, 1105, 1877], "text": "424"}]}, {"boundingBox": [67, 1915, 327, 1918, 326, 1950, 66, 1946], "text": "U. Los Angeles", "words": [{"boundingBox": [69, 1915, 108, 1917, 108, 1946, 69, 1944], "text": "U."}, {"boundingBox": [136, 1917, 192, 1919, 193, 1948, 136, 1947], "text": "Los"}, {"boundingBox": [206, 1919, 325, 1919, 325, 1947, 206, 1948], "text": "Angeles"}]}, {"boundingBox": [577, 1916, 615, 1914, 616, 1943, 578, 1945], "text": "70", "words": [{"boundingBox": [580, 1915, 613, 1914, 614, 1943, 581, 1944], "text": "70"}]}, {"boundingBox": [849, 1915, 888, 1914, 888, 1940, 849, 1941], "text": "60", "words": [{"boundingBox": [851, 1914, 886, 1914, 887, 1940, 852, 1940], "text": "60"}]}, {"boundingBox": [1091, 1917, 1157, 1917, 1157, 1943, 1091, 1945], "text": ". 653", "words": [{"boundingBox": [1090, 1916, 1099, 1916, 1100, 1944, 1090, 1944], "text": "."}, {"boundingBox": [1105, 1916, 1155, 1916, 1156, 1944, 1105, 1944], "text": "653"}]}, {"boundingBox": [69, 1983, 230, 1986, 229, 2015, 68, 2012], "text": "V. Miami", "words": [{"boundingBox": [69, 1985, 105, 1986, 106, 2012, 70, 2011], "text": "V."}, {"boundingBox": [135, 1986, 225, 1986, 226, 2014, 135, 2013], "text": "Miami"}]}, {"boundingBox": [577, 1982, 615, 1981, 615, 2010, 577, 2010], "text": "51", "words": [{"boundingBox": [580, 1980, 613, 1980, 613, 2009, 580, 2009], "text": "51"}]}, {"boundingBox": [848, 1982, 885, 1981, 885, 2004, 848, 2005], "text": "54", "words": [{"boundingBox": [853, 1981, 884, 1981, 884, 2004, 854, 2004], "text": "54"}]}, {"boundingBox": [1091, 1985, 1157, 1983, 1159, 2010, 1094, 2012], "text": ".583", "words": [{"boundingBox": [1091, 1984, 1156, 1982, 1157, 2009, 1092, 2011], "text": ".583"}]}, {"boundingBox": [66, 2052, 277, 2053, 276, 2083, 65, 2082], "text": "All Combined", "words": [{"boundingBox": [70, 2053, 125, 2055, 125, 2083, 70, 2082], "text": "All"}, {"boundingBox": [138, 2055, 277, 2053, 277, 2083, 138, 2084], "text": "Combined"}]}, {"boundingBox": [546, 2048, 607, 2052, 606, 2080, 545, 2076], "text": "4077", "words": [{"boundingBox": [547, 2048, 605, 2051, 603, 2079, 546, 2075], "text": "4077"}]}, {"boundingBox": [817, 2051, 884, 2052, 883, 2077, 817, 2075], "text": "4051", "words": [{"boundingBox": [818, 2050, 883, 2051, 883, 2076, 818, 2075], "text": "4051"}]}, {"boundingBox": [1090, 2053, 1153, 2053, 1154, 2079, 1090, 2080], "text": ". 636", "words": [{"boundingBox": [1091, 2052, 1098, 2052, 1098, 2079, 1091, 2079], "text": "."}, {"boundingBox": [1104, 2052, 1152, 2052, 1152, 2079, 1104, 2079], "text": "636"}]}, {"boundingBox": [409, 2244, 1364, 2243, 1364, 2272, 410, 2274], "text": "Source: https://www.industrydocuments.ucsf.edu/docs/gxxh0227", "words": [{"boundingBox": [418, 2245, 532, 2245, 532, 2274, 419, 2275], "text": "Source:"}, {"boundingBox": [538, 2245, 1363, 2243, 1362, 2274, 538, 2274], "text": "https://www.industrydocuments.ucsf.edu/docs/gxxh0227"}]}]}]}