{"status": "Succeeded", "recognitionResults": [{"page": 1, "clockwiseOrientation": 359.66, "width": 1790, "height": 2890, "unit": "pixel", "lines": [{"boundingBox": [92, 73, 258, 75, 257, 98, 91, 95], "text": "PROVIDER NUMBERS", "words": [{"boundingBox": [93, 75, 172, 75, 172, 95, 94, 96], "text": "PROVIDER"}, {"boundingBox": [176, 75, 255, 77, 253, 98, 176, 95], "text": "NUMBERS"}]}, {"boundingBox": [134, 95, 301, 96, 300, 116, 133, 115], "text": "MEDICARE: 26:7005", "words": [{"boundingBox": [143, 96, 230, 96, 229, 116, 142, 115], "text": "MEDICARE:"}, {"boundingBox": [234, 96, 300, 96, 299, 116, 233, 116], "text": "26:7005"}]}, {"boundingBox": [346, 72, 518, 73, 517, 98, 345, 98], "text": "PATIENT'S CLINIC NO .", "words": [{"boundingBox": [349, 74, 427, 73, 427, 98, 349, 98], "text": "PATIENT'S"}, {"boundingBox": [432, 73, 481, 73, 481, 98, 432, 98], "text": "CLINIC"}, {"boundingBox": [486, 73, 509, 73, 508, 98, 486, 98], "text": "NO"}, {"boundingBox": [513, 74, 516, 74, 516, 98, 513, 98], "text": "."}]}, {"boundingBox": [588, 78, 1381, 68, 1382, 105, 588, 115], "text": "REQUEST FOR HOME HEALTH SERVICE DATE PLAN ESTABLISHED", "words": [{"boundingBox": [592, 78, 735, 79, 735, 111, 593, 107], "text": "REQUEST"}, {"boundingBox": [742, 79, 804, 79, 805, 112, 743, 111], "text": "FOR"}, {"boundingBox": [816, 79, 915, 78, 915, 112, 816, 112], "text": "HOME"}, {"boundingBox": [925, 78, 1040, 77, 1039, 111, 925, 112], "text": "HEALTH"}, {"boundingBox": [1057, 77, 1186, 75, 1185, 106, 1056, 110], "text": "SERVICE"}, {"boundingBox": [1196, 74, 1235, 74, 1234, 104, 1195, 106], "text": "DATE"}, {"boundingBox": [1241, 74, 1280, 73, 1279, 102, 1240, 104], "text": "PLAN"}, {"boundingBox": [1286, 73, 1382, 70, 1380, 97, 1285, 102], "text": "ESTABLISHED"}]}, {"boundingBox": [1470, 72, 1595, 72, 1595, 95, 1471, 96], "text": "DATE REFERRAL", "words": [{"boundingBox": [1475, 74, 1516, 73, 1516, 97, 1476, 97], "text": "DATE"}, {"boundingBox": [1521, 73, 1595, 72, 1594, 97, 1521, 97], "text": "REFERRAL"}]}, {"boundingBox": [137, 116, 269, 114, 270, 136, 138, 138], "text": "MEDICAID : 83:6", "words": [{"boundingBox": [143, 118, 217, 116, 216, 137, 142, 139], "text": "MEDICAID"}, {"boundingBox": [221, 116, 228, 116, 227, 137, 220, 137], "text": ":"}, {"boundingBox": [232, 116, 269, 116, 268, 137, 231, 137], "text": "83:6"}]}, {"boundingBox": [82, 139, 244, 137, 245, 159, 83, 160], "text": "MEDICARE NUMBER", "words": [{"boundingBox": [95, 139, 175, 140, 174, 160, 95, 161], "text": "MEDICARE"}, {"boundingBox": [179, 140, 244, 138, 243, 159, 178, 160], "text": "NUMBER"}]}, {"boundingBox": [348, 141, 500, 140, 501, 160, 349, 162], "text": "MEDICAID NUMBER", "words": [{"boundingBox": [353, 142, 430, 141, 431, 160, 353, 162], "text": "MEDICAID"}, {"boundingBox": [435, 141, 500, 142, 500, 160, 436, 160], "text": "NUMBER"}]}, {"boundingBox": [585, 118, 644, 113, 645, 176, 586, 181], "text": "O", "words": [{"boundingBox": [584, 118, 625, 114, 631, 176, 589, 179], "text": "O"}]}, {"boundingBox": [716, 114, 1049, 115, 1048, 144, 715, 143], "text": "THE VISITING NURSE ASSOCIATION", "words": [{"boundingBox": [728, 116, 765, 116, 764, 143, 727, 142], "text": "THE"}, {"boundingBox": [770, 116, 851, 117, 851, 144, 769, 143], "text": "VISITING"}, {"boundingBox": [856, 117, 923, 117, 923, 144, 856, 144], "text": "NURSE"}, {"boundingBox": [928, 117, 1048, 115, 1049, 143, 928, 144], "text": "ASSOCIATION"}]}, {"boundingBox": [770, 144, 1005, 144, 1005, 170, 771, 171], "text": "OF GREATER ST. LOUIS", "words": [{"boundingBox": [783, 147, 810, 147, 810, 170, 783, 169], "text": "OF"}, {"boundingBox": [814, 147, 897, 147, 897, 172, 814, 170], "text": "GREATER"}, {"boundingBox": [904, 147, 935, 146, 935, 172, 904, 172], "text": "ST."}, {"boundingBox": [940, 146, 999, 145, 999, 171, 940, 172], "text": "LOUIS"}]}, {"boundingBox": [1180, 131, 1350, 130, 1351, 163, 1181, 164], "text": "DATE CARE BEGAN", "words": [{"boundingBox": [1196, 132, 1237, 134, 1236, 163, 1195, 164], "text": "DATE"}, {"boundingBox": [1243, 134, 1284, 136, 1283, 161, 1242, 162], "text": "CARE"}, {"boundingBox": [1291, 136, 1351, 136, 1351, 160, 1290, 161], "text": "BEGAN"}]}, {"boundingBox": [1472, 139, 1633, 140, 1632, 162, 1471, 161], "text": "DATE OF RENEWAL", "words": [{"boundingBox": [1476, 141, 1519, 141, 1519, 160, 1476, 160], "text": "DATE"}, {"boundingBox": [1522, 141, 1546, 141, 1546, 160, 1522, 160], "text": "OF"}, {"boundingBox": [1550, 141, 1630, 140, 1630, 162, 1550, 161], "text": "RENEWAL"}]}, {"boundingBox": [599, 173, 1172, 173, 1172, 202, 600, 203], "text": "1129 MACKLIND AVE., ST. LOUIS, MO. 63110", "words": [{"boundingBox": [602, 174, 662, 174, 664, 203, 604, 203], "text": "1129"}, {"boundingBox": [668, 174, 804, 175, 805, 202, 670, 203], "text": "MACKLIND"}, {"boundingBox": [818, 175, 887, 175, 888, 202, 818, 202], "text": "AVE.,"}, {"boundingBox": [893, 175, 932, 175, 932, 202, 894, 202], "text": "ST."}, {"boundingBox": [938, 175, 1027, 175, 1027, 202, 938, 202], "text": "LOUIS,"}, {"boundingBox": [1033, 175, 1093, 174, 1093, 203, 1033, 202], "text": "MO."}, {"boundingBox": [1099, 174, 1171, 173, 1170, 203, 1099, 203], "text": "63110"}]}, {"boundingBox": [90, 208, 259, 207, 260, 229, 91, 230], "text": "PATIENT'S LAST NAME", "words": [{"boundingBox": [93, 208, 170, 208, 170, 230, 93, 230], "text": "PATIENT'S"}, {"boundingBox": [174, 208, 212, 208, 211, 229, 174, 230], "text": "LAST"}, {"boundingBox": [216, 208, 260, 209, 259, 229, 216, 229], "text": "NAME"}]}, {"boundingBox": [456, 206, 552, 205, 553, 227, 457, 228], "text": "FIRST NAME", "words": [{"boundingBox": [461, 207, 501, 207, 500, 228, 461, 228], "text": "FIRST"}, {"boundingBox": [505, 207, 553, 206, 552, 228, 505, 228], "text": "NAME"}]}, {"boundingBox": [700, 208, 927, 204, 928, 227, 701, 232], "text": "M. I . PERMANENT ADDRESS", "words": [{"boundingBox": [706, 210, 719, 209, 719, 232, 706, 232], "text": "M."}, {"boundingBox": [724, 209, 724, 209, 724, 232, 724, 232], "text": "I", "confidence": "Low"}, {"boundingBox": [728, 209, 743, 209, 743, 231, 728, 231], "text": "."}, {"boundingBox": [753, 208, 849, 206, 849, 229, 753, 231], "text": "PERMANENT"}, {"boundingBox": [853, 206, 927, 206, 928, 228, 854, 229], "text": "ADDRESS"}]}, {"boundingBox": [1285, 208, 1361, 205, 1362, 228, 1286, 231], "text": "ZIP CODE", "words": [{"boundingBox": [1286, 211, 1311, 209, 1311, 230, 1287, 231], "text": "ZIP"}, {"boundingBox": [1315, 208, 1362, 208, 1362, 230, 1315, 230], "text": "CODE"}]}, {"boundingBox": [1477, 205, 1638, 207, 1637, 230, 1476, 228], "text": "TELEPHONE NUMBER", "words": [{"boundingBox": [1477, 206, 1566, 207, 1565, 230, 1477, 228], "text": "TELEPHONE"}, {"boundingBox": [1571, 207, 1638, 208, 1636, 230, 1570, 230], "text": "NUMBER"}]}, {"boundingBox": [127, 270, 182, 273, 181, 295, 126, 292], "text": "SEX", "words": [{"boundingBox": [143, 270, 175, 272, 174, 294, 141, 292], "text": "SEX"}]}, {"boundingBox": [219, 272, 317, 273, 316, 295, 218, 294], "text": "BIRTH DATE", "words": [{"boundingBox": [229, 274, 272, 274, 272, 295, 229, 294], "text": "BIRTH"}, {"boundingBox": [278, 274, 316, 273, 315, 295, 278, 295], "text": "DATE"}]}, {"boundingBox": [516, 272, 657, 274, 657, 302, 515, 299], "text": "MARITAL STATUS", "words": [{"boundingBox": [518, 276, 588, 274, 588, 298, 519, 297], "text": "MARITAL"}, {"boundingBox": [592, 274, 655, 275, 654, 302, 591, 298], "text": "STATUS"}]}, {"boundingBox": [753, 274, 1067, 271, 1068, 296, 754, 298], "text": "ADDRESS WHERE VNA TO VISIT PATIENT", "words": [{"boundingBox": [755, 275, 827, 275, 827, 298, 756, 299], "text": "ADDRESS"}, {"boundingBox": [832, 275, 888, 275, 889, 297, 832, 298], "text": "WHERE"}, {"boundingBox": [893, 275, 929, 275, 930, 297, 893, 297], "text": "VNA"}, {"boundingBox": [934, 274, 957, 274, 957, 296, 934, 297], "text": "TO"}, {"boundingBox": [961, 274, 999, 273, 1000, 296, 962, 296], "text": "VISIT"}, {"boundingBox": [1004, 273, 1066, 272, 1067, 296, 1005, 296], "text": "PATIENT"}]}, {"boundingBox": [1282, 277, 1360, 273, 1361, 294, 1283, 298], "text": "ZIP CODE", "words": [{"boundingBox": [1286, 278, 1311, 276, 1311, 296, 1286, 298], "text": "ZIP"}, {"boundingBox": [1315, 276, 1361, 275, 1361, 295, 1315, 296], "text": "CODE"}]}, {"boundingBox": [1473, 276, 1637, 275, 1638, 296, 1474, 297], "text": "TELEPHONE NUMBER", "words": [{"boundingBox": [1477, 276, 1566, 276, 1566, 297, 1476, 297], "text": "TELEPHONE"}, {"boundingBox": [1570, 276, 1637, 276, 1637, 295, 1570, 297], "text": "NUMBER"}]}, {"boundingBox": [92, 339, 259, 338, 260, 363, 93, 364], "text": "RESPONSIBLE PERSON", "words": [{"boundingBox": [93, 340, 195, 340, 194, 364, 93, 365], "text": "RESPONSIBLE"}, {"boundingBox": [200, 340, 259, 339, 258, 364, 199, 364], "text": "PERSON"}]}, {"boundingBox": [755, 343, 821, 340, 823, 362, 757, 366], "text": "ADDRESS", "words": [{"boundingBox": [757, 345, 821, 342, 821, 364, 757, 365], "text": "ADDRESS"}]}, {"boundingBox": [1284, 344, 1359, 342, 1360, 362, 1285, 365], "text": "ZIP CODE", "words": [{"boundingBox": [1285, 346, 1310, 344, 1310, 364, 1285, 365], "text": "ZIP"}, {"boundingBox": [1314, 344, 1359, 344, 1359, 363, 1314, 363], "text": "CODE"}]}, {"boundingBox": [1475, 342, 1638, 342, 1638, 364, 1476, 365], "text": "TELEPHONE NUMBER", "words": [{"boundingBox": [1478, 344, 1567, 345, 1566, 365, 1476, 362], "text": "TELEPHONE"}, {"boundingBox": [1571, 344, 1637, 342, 1635, 364, 1569, 365], "text": "NUMBER"}]}, {"boundingBox": [88, 407, 174, 405, 175, 428, 89, 430], "text": "PHYSICIAN", "words": [{"boundingBox": [93, 407, 174, 407, 174, 429, 93, 430], "text": "PHYSICIAN"}]}, {"boundingBox": [748, 409, 820, 405, 822, 428, 750, 431], "text": "ADDRESS", "words": [{"boundingBox": [754, 409, 821, 406, 821, 428, 755, 431], "text": "ADDRESS"}]}, {"boundingBox": [1474, 411, 1637, 409, 1637, 430, 1475, 433], "text": "TELEPHONE NUMBER", "words": [{"boundingBox": [1477, 412, 1566, 412, 1566, 432, 1477, 431], "text": "TELEPHONE"}, {"boundingBox": [1570, 411, 1638, 409, 1637, 429, 1569, 432], "text": "NUMBER"}]}, {"boundingBox": [88, 477, 309, 476, 310, 498, 89, 499], "text": "HOSPITAL OR CARE FACILITY", "words": [{"boundingBox": [92, 477, 168, 477, 168, 499, 92, 499], "text": "HOSPITAL"}, {"boundingBox": [172, 477, 197, 477, 196, 499, 172, 499], "text": "OR"}, {"boundingBox": [201, 477, 243, 477, 242, 499, 201, 499], "text": "CARE"}, {"boundingBox": [247, 477, 310, 477, 308, 499, 247, 499], "text": "FACILITY"}]}, {"boundingBox": [583, 478, 655, 475, 656, 495, 584, 498], "text": "DIVISION", "words": [{"boundingBox": [584, 478, 656, 477, 654, 497, 584, 498], "text": "DIVISION"}]}, {"boundingBox": [749, 476, 819, 475, 820, 495, 750, 497], "text": "ADDRESS", "words": [{"boundingBox": [755, 477, 819, 476, 819, 497, 755, 497], "text": "ADDRESS", "confidence": "Low"}]}, {"boundingBox": [1241, 475, 1380, 476, 1379, 498, 1240, 496], "text": "ADMISSION DATE", "words": [{"boundingBox": [1245, 477, 1334, 477, 1333, 496, 1245, 496], "text": "ADMISSION"}, {"boundingBox": [1341, 477, 1380, 478, 1379, 498, 1341, 497], "text": "DATE"}]}, {"boundingBox": [1474, 476, 1608, 477, 1607, 499, 1473, 498], "text": "DISCHARGE DATE", "words": [{"boundingBox": [1476, 477, 1568, 477, 1567, 499, 1475, 498], "text": "DISCHARGE"}, {"boundingBox": [1572, 477, 1608, 478, 1608, 499, 1571, 499], "text": "DATE"}]}, {"boundingBox": [86, 542, 260, 542, 259, 565, 85, 564], "text": "DIAGNOSIS: PRIMARY", "words": [{"boundingBox": [92, 542, 189, 544, 188, 565, 92, 563], "text": "DIAGNOSIS:"}, {"boundingBox": [193, 544, 259, 543, 258, 563, 192, 565], "text": "PRIMARY"}]}, {"boundingBox": [1053, 548, 1250, 546, 1251, 571, 1054, 572], "text": "PROGNOSIS: GOOD", "words": [{"boundingBox": [1054, 549, 1161, 548, 1161, 572, 1054, 572], "text": "PROGNOSIS:"}, {"boundingBox": [1195, 547, 1251, 547, 1251, 571, 1195, 572], "text": "GOOD"}]}, {"boundingBox": [1361, 546, 1440, 543, 1442, 570, 1363, 574], "text": "POOR", "words": [{"boundingBox": [1391, 546, 1441, 546, 1442, 569, 1392, 572], "text": "POOR"}]}, {"boundingBox": [1566, 549, 1681, 544, 1683, 568, 1568, 574], "text": "GUARDED", "words": [{"boundingBox": [1595, 548, 1676, 546, 1676, 568, 1595, 572], "text": "GUARDED"}]}, {"boundingBox": [1053, 582, 1141, 582, 1140, 611, 1052, 610], "text": "OTHER", "words": [{"boundingBox": [1089, 583, 1141, 584, 1140, 611, 1089, 611], "text": "OTHER"}]}, {"boundingBox": [1048, 613, 1145, 614, 1144, 639, 1047, 638], "text": "DIAGNOSIS :", "words": [{"boundingBox": [1053, 614, 1138, 615, 1138, 639, 1053, 639], "text": "DIAGNOSIS"}, {"boundingBox": [1143, 615, 1145, 615, 1144, 640, 1143, 639], "text": ":"}]}, {"boundingBox": [1413, 617, 1477, 614, 1478, 634, 1414, 637], "text": "KNOWN", "words": [{"boundingBox": [1414, 618, 1475, 615, 1476, 634, 1416, 637], "text": "KNOWN", "confidence": "Low"}]}, {"boundingBox": [93, 657, 190, 657, 190, 678, 93, 678], "text": "SECONDARY", "words": [{"boundingBox": [94, 657, 190, 657, 189, 678, 95, 678], "text": "SECONDARY"}]}, {"boundingBox": [1048, 648, 1367, 643, 1368, 673, 1049, 677], "text": "KNOWN TO PATIENT YES NO", "words": [{"boundingBox": [1052, 652, 1120, 650, 1120, 674, 1052, 674], "text": "KNOWN"}, {"boundingBox": [1124, 650, 1147, 649, 1148, 674, 1124, 674], "text": "TO"}, {"boundingBox": [1152, 649, 1221, 647, 1221, 674, 1152, 674], "text": "PATIENT"}, {"boundingBox": [1261, 646, 1295, 645, 1295, 674, 1262, 674], "text": "YES"}, {"boundingBox": [1338, 644, 1367, 644, 1368, 674, 1339, 674], "text": "NO"}]}, {"boundingBox": [1421, 648, 1473, 650, 1474, 673, 1422, 672], "text": "FAMILY", "words": [{"boundingBox": [1421, 647, 1473, 648, 1473, 672, 1420, 671], "text": "FAMILY", "confidence": "Low"}]}, {"boundingBox": [1484, 640, 1631, 643, 1630, 676, 1483, 674], "text": "YES NO", "words": [{"boundingBox": [1527, 643, 1565, 643, 1566, 676, 1528, 675], "text": "YES"}, {"boundingBox": [1601, 643, 1629, 643, 1630, 677, 1602, 677], "text": "NO"}]}, {"boundingBox": [1053, 684, 1275, 681, 1276, 704, 1053, 707], "text": "PATIENT/FAMILY NOTIFIED", "words": [{"boundingBox": [1053, 684, 1195, 683, 1195, 704, 1055, 707], "text": "PATIENT/FAMILY"}, {"boundingBox": [1200, 683, 1276, 683, 1274, 703, 1199, 704], "text": "NOTIFIED"}]}, {"boundingBox": [1050, 707, 1251, 706, 1252, 728, 1051, 729], "text": "VNA REFERRAL MADE:", "words": [{"boundingBox": [1054, 707, 1095, 708, 1095, 729, 1054, 730], "text": "VNA"}, {"boundingBox": [1099, 708, 1180, 708, 1180, 729, 1099, 729], "text": "REFERRAL"}, {"boundingBox": [1184, 708, 1247, 708, 1247, 728, 1184, 729], "text": "MADE:"}]}, {"boundingBox": [1501, 694, 1635, 697, 1635, 733, 1500, 730], "text": "YES NO", "words": [{"boundingBox": [1529, 696, 1569, 696, 1569, 732, 1528, 731], "text": "YES", "confidence": "Low"}, {"boundingBox": [1603, 697, 1635, 697, 1634, 733, 1603, 733], "text": "NO"}]}, {"boundingBox": [87, 756, 166, 758, 165, 778, 86, 776], "text": "SURGERY", "words": [{"boundingBox": [93, 758, 166, 760, 164, 779, 93, 777], "text": "SURGERY"}]}, {"boundingBox": [87, 776, 144, 775, 145, 792, 88, 794], "text": "DATE", "words": [{"boundingBox": [93, 777, 136, 776, 135, 793, 92, 794], "text": "DATE"}]}, {"boundingBox": [1049, 751, 1345, 752, 1344, 777, 1048, 776], "text": "LIMITATION OF FUNCTION (AS BLIND)", "words": [{"boundingBox": [1052, 753, 1142, 754, 1142, 776, 1052, 774], "text": "LIMITATION"}, {"boundingBox": [1149, 754, 1172, 754, 1172, 777, 1149, 776], "text": "OF"}, {"boundingBox": [1176, 754, 1257, 754, 1257, 777, 1176, 777], "text": "FUNCTION"}, {"boundingBox": [1262, 754, 1290, 753, 1290, 777, 1261, 777], "text": "(AS"}, {"boundingBox": [1294, 753, 1344, 752, 1344, 776, 1294, 777], "text": "BLIND)"}]}, {"boundingBox": [1483, 744, 1673, 741, 1673, 771, 1484, 775], "text": "BILLING COPY", "words": [{"boundingBox": [1492, 746, 1590, 744, 1589, 773, 1491, 773], "text": "BILLING"}, {"boundingBox": [1595, 744, 1658, 742, 1657, 772, 1594, 773], "text": "COPY"}]}, {"boundingBox": [86, 997, 89, 824, 111, 825, 109, 998], "text": "QZ --4- - 30>", "words": [{"boundingBox": [88, 962, 90, 933, 110, 934, 109, 963], "text": "QZ", "confidence": "Low"}, {"boundingBox": [90, 929, 91, 885, 110, 886, 110, 930], "text": "--4-", "confidence": "Low"}, {"boundingBox": [91, 881, 91, 869, 110, 871, 110, 882], "text": "-"}, {"boundingBox": [91, 865, 91, 825, 110, 827, 110, 866], "text": "30>", "confidence": "Low"}]}, {"boundingBox": [104, 904, 108, 826, 125, 827, 121, 905], "text": "- come", "words": [{"boundingBox": [107, 905, 106, 895, 122, 894, 123, 904], "text": "-"}, {"boundingBox": [106, 888, 112, 829, 125, 831, 121, 888], "text": "come", "confidence": "Low"}]}, {"boundingBox": [175, 829, 245, 830, 244, 853, 174, 851], "text": "SERVICE", "words": [{"boundingBox": [183, 831, 244, 833, 242, 853, 182, 851], "text": "SERVICE"}]}, {"boundingBox": [332, 824, 430, 820, 431, 841, 333, 845], "text": "FREQUENCY", "words": [{"boundingBox": [336, 824, 431, 821, 431, 841, 336, 845], "text": "FREQUENCY"}]}, {"boundingBox": [341, 843, 421, 842, 422, 862, 342, 863], "text": "OF VISITS", "words": [{"boundingBox": [346, 843, 369, 843, 369, 863, 346, 863], "text": "OF"}, {"boundingBox": [373, 843, 421, 843, 421, 862, 373, 863], "text": "VISITS"}]}, {"boundingBox": [548, 823, 639, 821, 639, 840, 549, 843], "text": "DURATION", "words": [{"boundingBox": [553, 824, 636, 821, 636, 840, 554, 842], "text": "DURATION"}]}, {"boundingBox": [557, 841, 637, 845, 636, 863, 556, 858], "text": "OF NEED", "words": [{"boundingBox": [561, 842, 587, 843, 586, 860, 562, 859], "text": "OF"}, {"boundingBox": [590, 843, 632, 845, 630, 863, 590, 860], "text": "NEED"}]}, {"boundingBox": [731, 830, 822, 831, 822, 853, 730, 851], "text": "ACTIVITIES", "words": [{"boundingBox": [735, 831, 821, 832, 820, 854, 735, 852], "text": "ACTIVITIES"}]}, {"boundingBox": [848, 831, 905, 830, 905, 850, 848, 851], "text": "ALONE", "words": [{"boundingBox": [850, 830, 903, 830, 903, 850, 850, 850], "text": "ALONE"}]}, {"boundingBox": [945, 821, 1138, 822, 1137, 843, 945, 843], "text": "ASSISTANCE OR DEVICE", "words": [{"boundingBox": [954, 823, 1051, 822, 1050, 842, 953, 843], "text": "ASSISTANCE"}, {"boundingBox": [1055, 822, 1079, 823, 1079, 842, 1054, 842], "text": "OR"}, {"boundingBox": [1083, 823, 1138, 824, 1137, 843, 1083, 842], "text": "DEVICE"}]}, {"boundingBox": [1007, 843, 1080, 844, 1079, 862, 1006, 861], "text": "(NAME)", "words": [{"boundingBox": [1018, 844, 1080, 845, 1079, 862, 1018, 861], "text": "(NAME)"}]}, {"boundingBox": [1279, 832, 1376, 830, 1377, 851, 1280, 853], "text": "EQUIPMENT", "words": [{"boundingBox": [1282, 833, 1377, 831, 1377, 851, 1282, 853], "text": "EQUIPMENT"}]}, {"boundingBox": [1533, 823, 1623, 821, 1624, 841, 1534, 844], "text": "DURATION", "words": [{"boundingBox": [1535, 825, 1619, 822, 1619, 842, 1536, 844], "text": "DURATION"}]}, {"boundingBox": [1533, 844, 1614, 842, 1615, 862, 1534, 865], "text": "OF NEED", "words": [{"boundingBox": [1544, 845, 1567, 844, 1566, 864, 1544, 865], "text": "OF"}, {"boundingBox": [1571, 843, 1615, 843, 1615, 864, 1570, 864], "text": "NEED"}]}, {"boundingBox": [145, 881, 222, 880, 223, 902, 146, 903], "text": "SK NURSE", "words": [{"boundingBox": [150, 881, 170, 882, 168, 903, 149, 902], "text": "SK"}, {"boundingBox": [174, 883, 223, 881, 221, 901, 172, 903], "text": "NURSE"}]}, {"boundingBox": [708, 883, 787, 880, 788, 901, 709, 904], "text": "UP AD LIB", "words": [{"boundingBox": [712, 883, 736, 883, 735, 904, 712, 903], "text": "UP"}, {"boundingBox": [740, 883, 763, 883, 763, 903, 740, 904], "text": "AD"}, {"boundingBox": [768, 882, 787, 881, 787, 902, 768, 903], "text": "LIB"}]}, {"boundingBox": [145, 914, 208, 913, 207, 937, 143, 935], "text": "PHYS . T .", "words": [{"boundingBox": [149, 912, 182, 912, 182, 936, 149, 936], "text": "PHYS"}, {"boundingBox": [187, 912, 194, 912, 194, 936, 187, 936], "text": "."}, {"boundingBox": [198, 912, 200, 912, 200, 936, 198, 936], "text": "T"}, {"boundingBox": [205, 912, 206, 912, 206, 936, 205, 936], "text": "."}]}, {"boundingBox": [1206, 885, 1338, 883, 1339, 908, 1207, 910], "text": "WHEELCHAIR", "words": [{"boundingBox": [1231, 885, 1338, 886, 1338, 908, 1232, 910], "text": "WHEELCHAIR"}]}, {"boundingBox": [709, 913, 766, 913, 766, 938, 708, 938], "text": "STAIRS", "words": [{"boundingBox": [714, 913, 764, 913, 764, 938, 714, 938], "text": "STAIRS"}]}, {"boundingBox": [1199, 918, 1299, 914, 1300, 938, 1200, 942], "text": "WALKER", "words": [{"boundingBox": [1233, 917, 1300, 915, 1300, 939, 1233, 941], "text": "WALKER"}]}, {"boundingBox": [146, 945, 223, 949, 222, 970, 145, 966], "text": "SPEECH T.", "words": [{"boundingBox": [151, 947, 209, 949, 207, 970, 150, 967], "text": "SPEECH"}, {"boundingBox": [214, 949, 223, 949, 221, 971, 212, 970], "text": "T.", "confidence": "Low"}]}, {"boundingBox": [704, 945, 813, 946, 812, 970, 704, 970], "text": "BATH ROOM", "words": [{"boundingBox": [712, 946, 753, 947, 753, 970, 712, 970], "text": "BATH"}, {"boundingBox": [758, 947, 811, 948, 812, 971, 758, 970], "text": "ROOM"}]}, {"boundingBox": [185, 982, 264, 979, 265, 1003, 186, 1006], "text": "OCCUP. T.", "words": [{"boundingBox": [191, 982, 253, 981, 253, 1004, 191, 1006], "text": "OCCUP."}, {"boundingBox": [257, 980, 265, 980, 265, 1004, 257, 1004], "text": "T.", "confidence": "Low"}]}, {"boundingBox": [1197, 952, 1255, 950, 1255, 974, 1198, 977], "text": "BEL", "words": [{"boundingBox": [1233, 950, 1253, 949, 1254, 974, 1234, 975], "text": "BEL", "confidence": "Low"}]}, {"boundingBox": [707, 980, 792, 979, 792, 1002, 708, 1004], "text": "TUB BATH", "words": [{"boundingBox": [712, 981, 743, 981, 744, 1003, 713, 1004], "text": "TUB"}, {"boundingBox": [747, 981, 792, 979, 793, 1002, 748, 1003], "text": "BATH"}]}, {"boundingBox": [184, 1013, 258, 1012, 259, 1035, 185, 1036], "text": "MED . S.S .", "words": [{"boundingBox": [190, 1014, 219, 1013, 219, 1036, 190, 1036], "text": "MED"}, {"boundingBox": [224, 1013, 231, 1013, 231, 1035, 224, 1035], "text": "."}, {"boundingBox": [235, 1013, 253, 1013, 253, 1035, 235, 1035], "text": "S.S"}, {"boundingBox": [257, 1013, 259, 1013, 259, 1035, 257, 1035], "text": "."}]}, {"boundingBox": [713, 1009, 780, 1003, 782, 1026, 715, 1031], "text": "OTHER", "words": [{"boundingBox": [722, 1008, 777, 1005, 777, 1026, 722, 1030], "text": "OTHER"}]}, {"boundingBox": [1197, 985, 1316, 981, 1317, 1009, 1198, 1013], "text": "SIDE RAILS", "words": [{"boundingBox": [1233, 984, 1265, 984, 1266, 1008, 1234, 1010], "text": "SIDE"}, {"boundingBox": [1271, 984, 1315, 985, 1316, 1008, 1272, 1008], "text": "RAILS"}]}, {"boundingBox": [185, 1047, 253, 1047, 253, 1071, 185, 1072], "text": "NUTRIT .", "words": [{"boundingBox": [188, 1046, 238, 1046, 238, 1071, 188, 1071], "text": "NUTRIT"}, {"boundingBox": [243, 1046, 251, 1046, 251, 1071, 243, 1071], "text": "."}]}, {"boundingBox": [712, 1021, 781, 1022, 780, 1044, 711, 1043], "text": "(SPECIFY)", "words": [{"boundingBox": [714, 1022, 781, 1023, 779, 1044, 712, 1043], "text": "(SPECIFY)", "confidence": "Low"}]}, {"boundingBox": [1197, 1014, 1317, 1014, 1316, 1041, 1196, 1040], "text": "COMMODE", "words": [{"boundingBox": [1232, 1015, 1316, 1016, 1316, 1039, 1233, 1041], "text": "COMMODE"}]}, {"boundingBox": [1226, 1048, 1362, 1047, 1362, 1070, 1227, 1071], "text": "OTHER (SPECIFY)", "words": [{"boundingBox": [1232, 1048, 1284, 1048, 1283, 1072, 1232, 1071], "text": "OTHER"}, {"boundingBox": [1288, 1049, 1361, 1048, 1361, 1071, 1288, 1072], "text": "(SPECIFY)", "confidence": "Low"}]}, {"boundingBox": [186, 1081, 266, 1082, 265, 1103, 185, 1101], "text": "H.H. AIDE", "words": [{"boundingBox": [187, 1081, 223, 1082, 224, 1102, 188, 1102], "text": "H.H."}, {"boundingBox": [227, 1082, 265, 1083, 265, 1102, 228, 1102], "text": "AIDE"}]}, {"boundingBox": [98, 1123, 134, 1125, 133, 1143, 97, 1141], "text": "G", "words": [{"boundingBox": [102, 1123, 114, 1123, 113, 1141, 101, 1141], "text": "G"}]}, {"boundingBox": [93, 1146, 253, 1148, 252, 1167, 92, 1165], "text": "PHYSICIAN'S ORDERS", "words": [{"boundingBox": [94, 1147, 190, 1149, 190, 1167, 93, 1165], "text": "PHYSICIAN'S"}, {"boundingBox": [195, 1149, 253, 1149, 252, 1166, 194, 1167], "text": "ORDERS"}]}, {"boundingBox": [1192, 1148, 1306, 1146, 1307, 1165, 1193, 1166], "text": "MEDICATIONS", "words": [{"boundingBox": [1194, 1148, 1306, 1147, 1306, 1165, 1194, 1166], "text": "MEDICATIONS"}]}, {"boundingBox": [1188, 1614, 1456, 1613, 1456, 1634, 1189, 1636], "text": "ALLERGIES (FOODS, DRUGS, ETC.)", "words": [{"boundingBox": [1193, 1615, 1272, 1615, 1273, 1635, 1194, 1635], "text": "ALLERGIES"}, {"boundingBox": [1276, 1615, 1347, 1615, 1348, 1635, 1277, 1635], "text": "(FOODS,"}, {"boundingBox": [1351, 1615, 1413, 1614, 1413, 1635, 1352, 1635], "text": "DRUGS,"}, {"boundingBox": [1417, 1614, 1456, 1613, 1456, 1635, 1417, 1635], "text": "ETC.)"}]}, {"boundingBox": [91, 1708, 200, 1707, 201, 1731, 92, 1732], "text": "OBSERVE FOR", "words": [{"boundingBox": [93, 1709, 165, 1708, 165, 1732, 94, 1733], "text": "OBSERVE"}, {"boundingBox": [170, 1708, 201, 1708, 200, 1732, 170, 1732], "text": "FOR"}]}, {"boundingBox": [1191, 1718, 1236, 1717, 1237, 1739, 1192, 1741], "text": "DIET :", "words": [{"boundingBox": [1193, 1717, 1222, 1716, 1223, 1739, 1194, 1740], "text": "DIET"}, {"boundingBox": [1226, 1716, 1236, 1716, 1236, 1739, 1227, 1739], "text": ":"}]}, {"boundingBox": [1195, 1750, 1255, 1749, 1256, 1774, 1195, 1776], "text": "REG.", "words": [{"boundingBox": [1222, 1749, 1254, 1748, 1255, 1774, 1222, 1775], "text": "REG.", "confidence": "Low"}]}, {"boundingBox": [1191, 1781, 1280, 1782, 1279, 1809, 1190, 1808], "text": "OTHER", "words": [{"boundingBox": [1224, 1782, 1279, 1783, 1280, 1809, 1224, 1809], "text": "OTHER"}]}, {"boundingBox": [1191, 1813, 1510, 1816, 1509, 1847, 1190, 1843], "text": "NUTRITIONAL INSTRUCTION NEEDED", "words": [{"boundingBox": [1221, 1815, 1324, 1820, 1324, 1843, 1222, 1844], "text": "NUTRITIONAL"}, {"boundingBox": [1330, 1820, 1436, 1822, 1435, 1843, 1329, 1843], "text": "INSTRUCTION"}, {"boundingBox": [1442, 1822, 1510, 1822, 1509, 1843, 1441, 1843], "text": "NEEDED"}]}, {"boundingBox": [91, 1878, 292, 1876, 293, 1899, 92, 1901], "text": "IMPROVEMENT EXPECTED", "words": [{"boundingBox": [93, 1879, 209, 1877, 209, 1900, 93, 1901], "text": "IMPROVEMENT"}, {"boundingBox": [213, 1877, 291, 1877, 290, 1900, 213, 1900], "text": "EXPECTED"}]}, {"boundingBox": [1191, 1847, 1443, 1848, 1442, 1877, 1190, 1875], "text": "DIET LIST GIVEN TO PATIENT", "words": [{"boundingBox": [1222, 1848, 1254, 1849, 1255, 1876, 1222, 1876], "text": "DIET"}, {"boundingBox": [1260, 1849, 1289, 1850, 1290, 1875, 1261, 1876], "text": "LIST"}, {"boundingBox": [1295, 1850, 1345, 1851, 1346, 1875, 1295, 1875], "text": "GIVEN"}, {"boundingBox": [1351, 1851, 1373, 1851, 1373, 1875, 1351, 1875], "text": "TO"}, {"boundingBox": [1378, 1852, 1442, 1852, 1442, 1874, 1378, 1875], "text": "PATIENT"}]}, {"boundingBox": [1193, 1887, 1261, 1889, 1261, 1911, 1193, 1911], "text": "ENEMAS:", "words": [{"boundingBox": [1194, 1887, 1260, 1887, 1259, 1911, 1194, 1910], "text": "ENEMAS:"}]}, {"boundingBox": [95, 1952, 441, 1950, 441, 1978, 96, 1981], "text": "CERTIFICATION: I HEREBY CERTIFY", "words": [{"boundingBox": [96, 1955, 248, 1954, 248, 1978, 97, 1979], "text": "CERTIFICATION:"}, {"boundingBox": [253, 1954, 259, 1954, 259, 1978, 253, 1978], "text": "I"}, {"boundingBox": [263, 1954, 328, 1953, 327, 1979, 263, 1978], "text": "HEREBY"}, {"boundingBox": [363, 1952, 427, 1950, 426, 1980, 362, 1979], "text": "CERTIFY"}]}, {"boundingBox": [1191, 1920, 1260, 1921, 1260, 1948, 1191, 1946], "text": "PRN", "words": [{"boundingBox": [1225, 1920, 1259, 1920, 1258, 1947, 1224, 1947], "text": "PRN"}]}, {"boundingBox": [475, 1950, 910, 1951, 909, 1979, 474, 1978], "text": "RECERTIFY: THAT THIS PATIENT IS \"HOMEBOUND.\"", "words": [{"boundingBox": [518, 1952, 599, 1953, 599, 1980, 518, 1979], "text": "RECERTIFY:"}, {"boundingBox": [604, 1953, 644, 1953, 645, 1980, 605, 1980], "text": "THAT"}, {"boundingBox": [650, 1953, 683, 1953, 683, 1980, 650, 1980], "text": "THIS"}, {"boundingBox": [689, 1953, 751, 1953, 751, 1980, 689, 1980], "text": "PATIENT"}, {"boundingBox": [757, 1953, 771, 1953, 771, 1980, 757, 1980], "text": "IS"}, {"boundingBox": [777, 1953, 909, 1951, 909, 1980, 777, 1980], "text": "\"HOMEBOUND.\""}]}, {"boundingBox": [95, 1981, 957, 1982, 956, 2008, 94, 2007], "text": "CARE IS TO TREAT ANY OF THE CONDITIONS FOR WHICH THE PATIENT RECEIVED HOSPITAL OR ECF CARE.", "words": [{"boundingBox": [131, 1983, 173, 1983, 172, 2007, 131, 2007], "text": "CARE"}, {"boundingBox": [177, 1983, 192, 1983, 192, 2007, 176, 2007], "text": "IS"}, {"boundingBox": [197, 1983, 222, 1983, 221, 2007, 196, 2007], "text": "TO"}, {"boundingBox": [226, 1983, 275, 1983, 274, 2007, 225, 2007], "text": "TREAT"}, {"boundingBox": [280, 1983, 313, 1983, 312, 2007, 279, 2007], "text": "ANY"}, {"boundingBox": [318, 1983, 341, 1983, 340, 2007, 317, 2007], "text": "OF"}, {"boundingBox": [345, 1983, 376, 1982, 375, 2007, 345, 2007], "text": "THE"}, {"boundingBox": [381, 1982, 483, 1982, 482, 2007, 380, 2007], "text": "CONDITIONS"}, {"boundingBox": [488, 1982, 521, 1982, 520, 2007, 487, 2007], "text": "FOR"}, {"boundingBox": [526, 1982, 584, 1982, 583, 2007, 525, 2007], "text": "WHICH"}, {"boundingBox": [588, 1982, 617, 1982, 617, 2008, 588, 2007], "text": "THE"}, {"boundingBox": [622, 1982, 685, 1982, 684, 2008, 621, 2008], "text": "PATIENT"}, {"boundingBox": [689, 1982, 764, 1982, 763, 2008, 689, 2008], "text": "RECEIVED"}, {"boundingBox": [769, 1982, 845, 1982, 844, 2008, 768, 2008], "text": "HOSPITAL"}, {"boundingBox": [850, 1982, 874, 1982, 874, 2008, 849, 2008], "text": "OR"}, {"boundingBox": [879, 1982, 909, 1982, 909, 2009, 878, 2008], "text": "ECF"}, {"boundingBox": [914, 1982, 957, 1982, 956, 2009, 913, 2009], "text": "CARE."}]}, {"boundingBox": [1182, 1960, 1249, 1961, 1248, 1983, 1181, 1982], "text": "TYPES:", "words": [{"boundingBox": [1194, 1961, 1248, 1962, 1248, 1984, 1194, 1983], "text": "TYPES:"}]}, {"boundingBox": [93, 2013, 284, 2011, 285, 2033, 93, 2035], "text": "DATE LAST SEEN BY ME", "words": [{"boundingBox": [98, 2013, 140, 2013, 140, 2034, 98, 2035], "text": "DATE"}, {"boundingBox": [144, 2013, 183, 2013, 183, 2034, 144, 2034], "text": "LAST"}, {"boundingBox": [188, 2013, 228, 2013, 227, 2033, 187, 2034], "text": "SEEN"}, {"boundingBox": [233, 2012, 251, 2012, 250, 2033, 232, 2033], "text": "BY"}, {"boundingBox": [256, 2012, 285, 2012, 283, 2033, 255, 2033], "text": "ME"}]}, {"boundingBox": [398, 2004, 634, 2003, 634, 2031, 399, 2032], "text": "PHYSICIAN'S SIGNATURE", "words": [{"boundingBox": [422, 2006, 522, 2008, 521, 2032, 421, 2030], "text": "PHYSICIAN'S"}, {"boundingBox": [527, 2008, 624, 2004, 623, 2030, 526, 2032], "text": "SIGNATURE"}]}, {"boundingBox": [1194, 1986, 1610, 1987, 1609, 2012, 1193, 2011], "text": "PROGRESS REPORTS REQUESTED YES NO", "words": [{"boundingBox": [1194, 1988, 1274, 1987, 1274, 2009, 1194, 2009], "text": "PROGRESS"}, {"boundingBox": [1278, 1987, 1346, 1987, 1346, 2010, 1278, 2009], "text": "REPORTS"}, {"boundingBox": [1350, 1987, 1442, 1987, 1442, 2010, 1350, 2010], "text": "REQUESTED"}, {"boundingBox": [1495, 1987, 1527, 1987, 1527, 2011, 1495, 2011], "text": "YES"}, {"boundingBox": [1583, 1987, 1609, 1987, 1609, 2013, 1582, 2012], "text": "NO"}]}, {"boundingBox": [1322, 2011, 1382, 2012, 1381, 2029, 1321, 2028], "text": "| DATE", "words": [{"boundingBox": [1324, 2012, 1330, 2012, 1329, 2028, 1323, 2028], "text": "|", "confidence": "Low"}, {"boundingBox": [1333, 2012, 1376, 2013, 1375, 2029, 1332, 2028], "text": "DATE"}]}, {"boundingBox": [91, 2090, 297, 2088, 297, 2107, 92, 2110], "text": "CLINIC APPOINTMENT AT:", "words": [{"boundingBox": [97, 2091, 148, 2091, 148, 2109, 97, 2110], "text": "CLINIC"}, {"boundingBox": [152, 2091, 266, 2089, 264, 2109, 151, 2109], "text": "APPOINTMENT"}, {"boundingBox": [270, 2089, 297, 2088, 295, 2109, 268, 2109], "text": "AT:"}]}, {"boundingBox": [1185, 2086, 1378, 2087, 1377, 2108, 1184, 2106], "text": "DATE OF APPOINTMENT", "words": [{"boundingBox": [1191, 2088, 1235, 2087, 1235, 2107, 1191, 2107], "text": "DATE"}, {"boundingBox": [1239, 2087, 1264, 2088, 1263, 2107, 1238, 2107], "text": "OF"}, {"boundingBox": [1268, 2088, 1377, 2090, 1376, 2107, 1267, 2107], "text": "APPOINTMENT"}]}, {"boundingBox": [467, 2153, 1086, 2155, 1085, 2190, 466, 2189], "text": "MEDICAL AND SOCIAL INFORMATION", "words": [{"boundingBox": [470, 2154, 619, 2155, 618, 2189, 469, 2188], "text": "MEDICAL"}, {"boundingBox": [628, 2155, 699, 2155, 698, 2190, 627, 2189], "text": "AND"}, {"boundingBox": [714, 2155, 839, 2155, 839, 2190, 714, 2190], "text": "SOCIAL"}, {"boundingBox": [846, 2155, 1079, 2155, 1079, 2190, 846, 2190], "text": "INFORMATION"}]}, {"boundingBox": [1551, 2166, 1601, 2165, 1602, 2185, 1552, 2186], "text": "DATE", "words": [{"boundingBox": [1558, 2165, 1601, 2164, 1601, 2184, 1558, 2185], "text": "DATE"}]}, {"boundingBox": [1485, 2212, 1670, 2213, 1669, 2235, 1484, 2235], "text": "SIGNATURE AND TITLE", "words": [{"boundingBox": [1490, 2213, 1581, 2213, 1580, 2235, 1491, 2236], "text": "SIGNATURE"}, {"boundingBox": [1585, 2213, 1622, 2213, 1622, 2235, 1585, 2235], "text": "AND"}, {"boundingBox": [1626, 2213, 1669, 2214, 1669, 2235, 1626, 2235], "text": "TITLE"}]}, {"boundingBox": [80, 2811, 221, 2810, 222, 2832, 81, 2833], "text": "FORM NO. MR-4A", "words": [{"boundingBox": [81, 2813, 126, 2811, 126, 2832, 82, 2833], "text": "FORM"}, {"boundingBox": [132, 2811, 166, 2811, 165, 2832, 131, 2832], "text": "NO."}, {"boundingBox": [170, 2811, 222, 2812, 220, 2833, 169, 2832], "text": "MR-4A"}]}, {"boundingBox": [411, 2850, 1367, 2849, 1368, 2881, 412, 2883], "text": "Source: https://www.industrydocuments.ucsf.edu/docs/mtvg0227", "words": [{"boundingBox": [419, 2852, 535, 2852, 536, 2883, 419, 2883], "text": "Source:"}, {"boundingBox": [541, 2852, 1368, 2851, 1367, 2882, 542, 2883], "text": "https://www.industrydocuments.ucsf.edu/docs/mtvg0227"}]}]}]}